[
  {
    "id": "cmjf25o9r0005wf98f2f9vvjl",
    "title": "Berpikir komputasional",
    "description": "",
    "type": "TEXT",
    "content": "Berpikir komputasional adalah",
    "createdAt": "2025-12-21T01:38:11.039Z",
    "courseId": "cmjefhau00005qq5n4g4250a3"
  },
  {
    "id": "cmjf25o9s0007wf9806idk4os",
    "title": "Berpikir komputasional",
    "description": "",
    "type": "TEXT",
    "content": "Berpikir komputasional adalah",
    "createdAt": "2025-12-21T01:38:11.038Z",
    "courseId": "cmjefh4lv000bl9yuyohe9xza"
  }
]